monarchopt/__init__.py
monarchopt/core.py
monarchopt/exceptions.py
monarchopt/utils.py
monarchopt/validators.py
monarchopt-0.1.4.dist-info/LICENSE
monarchopt-0.1.4.dist-info/METADATA
monarchopt-0.1.4.dist-info/WHEEL
monarchopt-0.1.4.dist-info/top_level.txt
monarchopt-0.1.4.dist-info/RECORD
